doc2dash/__init__.py
doc2dash/__main__.py
doc2dash/convert.py
doc2dash/docsets.py
doc2dash/output.py
doc2dash/parsers/__init__.py
doc2dash/parsers/intersphinx.py
doc2dash/parsers/intersphinx_inventory.py
doc2dash/parsers/patcher.py
doc2dash/parsers/types.py
doc2dash-3.1.0.dist-info/METADATA
doc2dash-3.1.0.dist-info/WHEEL
doc2dash-3.1.0.dist-info/entry_points.txt
doc2dash-3.1.0.dist-info/licenses/LICENSE
doc2dash-3.1.0.dist-info/RECORD
