Metadata-Version: 2.1
Name: doc2dash
Version: 3.1.0
Summary: Convert docs to the docset format.
Project-URL: Documentation, https://doc2dash.hynek.me/
Project-URL: Changelog, https://github.com/hynek/doc2dash/blob/main/CHANGELOG.md
Project-URL: GitHub, https://github.com/hynek/doc2dash
Project-URL: Funding, https://github.com/sponsors/hynek
Project-URL: Mastodon, https://mastodon.social/@hynek
Project-URL: Twitter, https://twitter.com/hynek
Author-email: Hynek Schlawack <hs@ox.cx>
License-Expression: MIT
License-File: LICENSE
Classifier: Development Status :: 5 - Production/Stable
Classifier: Environment :: Console
Classifier: License :: OSI Approved :: MIT License
Classifier: Programming Language :: Python :: 3.8
Classifier: Programming Language :: Python :: 3.9
Classifier: Programming Language :: Python :: 3.10
Classifier: Programming Language :: Python :: 3.11
Classifier: Programming Language :: Python :: 3.12
Classifier: Topic :: Software Development :: Documentation
Requires-Python: >=3.8
Requires-Dist: attrs>=23.2
Requires-Dist: beautifulsoup4
Requires-Dist: click>8
Requires-Dist: rich
Provides-Extra: dev
Requires-Dist: doc2dash[tests,typing]; extra == 'dev'
Requires-Dist: nox; extra == 'dev'
Provides-Extra: docs
Requires-Dist: mkdocs; extra == 'docs'
Requires-Dist: mkdocs-callouts; extra == 'docs'
Requires-Dist: mkdocs-click; extra == 'docs'
Requires-Dist: mkdocs-include-markdown-plugin; extra == 'docs'
Requires-Dist: mkdocs-material; extra == 'docs'
Requires-Dist: mkdocstrings[python]; extra == 'docs'
Provides-Extra: tests
Requires-Dist: coverage[toml]; extra == 'tests'
Requires-Dist: pytest; extra == 'tests'
Provides-Extra: typing
Requires-Dist: mypy; extra == 'typing'
Requires-Dist: types-urllib3; extra == 'typing'
